setup.cfg
setup.py
examples/__init__.py
examples/train_multi_gpu.py
examples/ga/__init__.py
examples/ga/custom_activation.py
examples/ga/custom_layer_activation.py
examples/ga/dataset.py
examples/ga/search_model_layout_and_params.py
examples/ga/search_model_params.py
minos/__init__.py
minos/tf_utils.py
minos/utils.py
minos/experiment/__init__.py
minos/experiment/experiment.py
minos/experiment/ga.py
minos/experiment/training.py
minos/model/__init__.py
minos/model/build.py
minos/model/design.py
minos/model/model.py
minos/model/parameter.py
minos/model/parameters.py
minos/search/__init__.py
minos/search/ga/__init__.py
minos/search/ga/ga_search.py
minos/train/__init__.py
minos/train/trainer.py
minos/train/utils.py
pyminos.egg-info/PKG-INFO
pyminos.egg-info/SOURCES.txt
pyminos.egg-info/dependency_links.txt
pyminos.egg-info/requires.txt
pyminos.egg-info/top_level.txt
tests/__init__.py
tests/fixtures.py
tests/model/__init__.py
tests/model/build_test.py
tests/model/design_test.py
tests/model/mix_test.py
tests/model/mutation_test.py
tests/model/parameters_test.py
tests/search/__init__.py
tests/search/ga_search_test.py
tests/train/__init__.py
tests/train/model_save_test.py
tests/train/model_train_test.py
tests/train/multidevice_model_train_test.py
tests/train/multiprocess_model_train_test.py