Metadata-Version: 1.0
Name: pyminos
Version: 0.5.1
Summary: Neural nets hyper parameters & architecture search with genetic algorithms
Home-page: https://github.com/guybedo/minos
Author: Julien Roch
Author-email: julien.roch@akalea.com
License: Apache
Keywords: keras,genetic algorithm,neural network,deep learning
Platform: UNKNOWN
